{
  "fallback": "minecraft:empty",
  "elements": [
    {
      "weight": 1,
      "element": {
        "element_type": "minecraft:single_pool_element",
        "location": "splendid_slimes:spawner/luminous_glowstone_1",
        "projection": "rigid",
        "processors": "minecraft:empty"
      }
    },
    {
      "weight": 1,
      "element": {
        "element_type": "minecraft:single_pool_element",
        "location": "splendid_slimes:spawner/luminous_glowstone_2",
        "projection": "rigid",
        "processors": "minecraft:empty"
      }
    },
    {
      "weight": 1,
      "element": {
        "element_type": "minecraft:single_pool_element",
        "location": "splendid_slimes:spawner/luminous_glowstone_3",
        "projection": "rigid",
        "processors": "minecraft:empty"
      }
    }
  ]
}